qubits/.DS_Store
qubits/.coverage
qubits/__init__.py
qubits/__version__.py
qubits/cl_utils.py
qubits/commonutils.py
qubits/datagenerator.py
qubits/default_settings.yaml
qubits/results.py
qubits/surveysim.py
qubits/universe.py
qubits/utKit.py
qubits/workspace.py
qubits/assets/.DS_Store
qubits/assets/SNOne_-_i-band.png
qubits/assets/dry_thesis_ch2.pdf
qubits/assets/example_results.png
qubits/assets/k_ir_at_z_=_0.3.png
qubits/resources/.DS_Store
qubits/resources/qubits_settings.yaml
qubits/resources/qubits_spectral_database/.DS_Store
qubits/resources/qubits_spectral_database/SNOne/.DS_Store
qubits/resources/qubits_spectral_database/SNOne/t+000.50.spec
qubits/resources/qubits_spectral_database/SNOne/t+010.00.spec
qubits/resources/qubits_spectral_database/SNOne/t+027.50.spec
qubits/resources/qubits_spectral_database/SNOne/t+050.00.spec
qubits/resources/qubits_spectral_database/SNOne/t+115.00.spec
qubits/resources/qubits_spectral_database/SNOne/t-021.00.spec
qubits/resources/qubits_spectral_database/SNTwo/.DS_Store
qubits/resources/qubits_spectral_database/SNTwo/t+014.00.spec
qubits/resources/qubits_spectral_database/SNTwo/t+038.00.spec
qubits/resources/qubits_spectral_database/SNTwo/t+065.00.spec
qubits/resources/qubits_spectral_database/SNTwo/t+185.00.spec
qubits/resources/qubits_spectral_database/SNTwo/t-001.50.spec
qubits/resources/qubits_spectral_database/SNTwo/t-015.00.spec
qubits/tests/__init__.py
qubits/tests/test_command_line.py
qubits/tests/test_workspace.py
qubits/tests/input/example_settings.yaml
qubits/tests/input/qubits_settings.yaml
qubits/tests/input/test_spectral_database/SNOne/t+012.50.spec
qubits/tests/input/test_spectral_database/SNOne/t+049.00.spec
qubits/tests/input/test_spectral_database/SNOne/t+101.00.spec
qubits/tests/input/test_spectral_database/SNOne/t+149.00.spec
qubits/tests/input/test_spectral_database/SNOne/t+201.00.spec
qubits/tests/input/test_spectral_database/SNOne/t+249.00.spec
qubits-0.3.4.dist-info/LICENSE.txt
qubits-0.3.4.dist-info/METADATA
qubits-0.3.4.dist-info/WHEEL
qubits-0.3.4.dist-info/entry_points.txt
qubits-0.3.4.dist-info/top_level.txt
qubits-0.3.4.dist-info/RECORD
