Metadata-Version: 2.1
Name: qubits
Version: 0.3.4
Summary: The Queen's University Belfast Imitation Transient Surveys
Home-page: https://github.com/thespacedoctor/qubits
Download-URL: https://github.com/thespacedoctor/qubits/archive/v0.3.4.zip
Author: David Young
Author-email: davidrobertyoung@gmail.com
License: MIT
Keywords: transient, astronomy, simulation
Classifier: Development Status :: 4 - Beta
Classifier: License :: OSI Approved :: MIT License
Classifier: Programming Language :: Python :: 2.7
Classifier: Topic :: Utilities
License-File: LICENSE.txt
Requires-Dist: pyyaml
Requires-Dist: qubits
Requires-Dist: fundamentals
Requires-Dist: pysynphot
Requires-Dist: astrocalc
